miniq/__init__.py
miniq/miniq.py
miniq/protobuf/__init__.py
miniq/protobuf/queue_pb2.py
miniq/protobuf/queue_pb2_grpc.py
miniq-0.0.2.dist-info/LICENSE
miniq-0.0.2.dist-info/METADATA
miniq-0.0.2.dist-info/WHEEL
miniq-0.0.2.dist-info/top_level.txt
miniq-0.0.2.dist-info/RECORD
